MingxiangdeQiji/Dockerfile
MingxiangdeQiji/README.md
MingxiangdeQiji/__init__.py
MingxiangdeQiji/__main__.py
MingxiangdeQiji/file.epub
MingxiangdeQiji/index.html
MingxiangdeQiji/css/__init__.py
MingxiangdeQiji/css/annotations.css
MingxiangdeQiji/css/main.css
MingxiangdeQiji/css/normalize.css
MingxiangdeQiji/css/popup.css
MingxiangdeQiji/font/__init__.py
MingxiangdeQiji/font/fontello.eot
MingxiangdeQiji/font/fontello.svg
MingxiangdeQiji/font/fontello.ttf
MingxiangdeQiji/font/fontello.woff
MingxiangdeQiji/img/__init__.py
MingxiangdeQiji/img/annotator-glyph-sprite.png
MingxiangdeQiji/img/annotator-icon-sprite.png
MingxiangdeQiji/img/apple-touch-icon.png
MingxiangdeQiji/img/cancelfullscreen.png
MingxiangdeQiji/img/close.png
MingxiangdeQiji/img/fullscreen.png
MingxiangdeQiji/img/loader.gif
MingxiangdeQiji/img/menu-icon.png
MingxiangdeQiji/img/save.png
MingxiangdeQiji/img/saved.png
MingxiangdeQiji/img/settings-s.png
MingxiangdeQiji/img/settings.png
MingxiangdeQiji/img/star.png
MingxiangdeQiji/js/__init__.py
MingxiangdeQiji/js/epub.js
MingxiangdeQiji/js/epub.min.js
MingxiangdeQiji/js/epub.min.map
MingxiangdeQiji/js/hooks.min.js
MingxiangdeQiji/js/hooks.min.map
MingxiangdeQiji/js/reader.js
MingxiangdeQiji/js/reader.js.map
MingxiangdeQiji/js/reader.min.js
MingxiangdeQiji/js/reader.min.map
MingxiangdeQiji/js/hooks/__init__.py
MingxiangdeQiji/js/hooks/extensions/__init__.py
MingxiangdeQiji/js/hooks/extensions/highlight.js
MingxiangdeQiji/js/libs/__init__.py
MingxiangdeQiji/js/libs/jquery.min.js
MingxiangdeQiji/js/libs/localforage.min.js
MingxiangdeQiji/js/libs/screenfull.js
MingxiangdeQiji/js/libs/screenfull.min.js
MingxiangdeQiji/js/libs/zip.min.js
MingxiangdeQiji/js/plugins/__init__.py
MingxiangdeQiji/js/plugins/hypothesis.js
MingxiangdeQiji/js/plugins/search.js
mingxiangde_qiji-2022.10.9.1.dist-info/METADATA
mingxiangde_qiji-2022.10.9.1.dist-info/WHEEL
mingxiangde_qiji-2022.10.9.1.dist-info/entry_points.txt
mingxiangde_qiji-2022.10.9.1.dist-info/top_level.txt
mingxiangde_qiji-2022.10.9.1.dist-info/RECORD
